{
  "country": "MMR",
  "alpha": 0.2,
  "n_constructs": 55,
  "hub_scores": {
    "acceptance_of_state_surveillance|WVS_H": 0.7907847367854333,
    "authoritarian_governance_tolerance|WVS_E": 0.7843813172165961,
    "autocracy_support|WVS_E": 0.7899263451662377,
    "basic_needs_deprivation|WVS_H": 0.7813581425203521,
    "child_qualities_autonomy_self_expression|WVS_A": 0.7911539784442909,
    "child_qualities_conformity_tradition|WVS_A": 0.787931013784601,
    "child_qualities_prosocial_diligence|WVS_A": 0.7888079459420545,
    "civic_dishonesty_tolerance|WVS_F": 0.783658777474924,
    "confidence_in_civil_society_organizations|WVS_E": 0.7859489032476935,
    "confidence_in_domestic_institutions|WVS_E": 0.7806840148046206,
    "confidence_in_international_organizations|WVS_E": 0.7932737026114282,
    "crime_victimization|WVS_H": 0.7883525274807842,
    "democratic_system_evaluation|WVS_E": 0.7899452403559761,
    "democratic_values_importance|WVS_E": 0.7906630389435878,
    "economic_ideology|WVS_E": 0.7942473249954501,
    "electoral_integrity|WVS_E": 0.7895711268794515,
    "existential_threat_worry|WVS_H": 3.686159985583082e-08,
    "familial_duty_obligations|WVS_D": 0.7734992874654286,
    "female_income_threat_to_marriage|WVS_D": 0.7834398377245073,
    "freedom_security_tradeoff_perception|WVS_H": 0.7869220134475824,
    "gender_role_traditionalism|WVS_D": 0.7706670808960833,
    "immigrant_origin_status|WVS_G": 3.686159985583082e-08,
    "importance_of_life_domains|WVS_A": 0.7924607893533282,
    "institutional_threat_perception|WVS_H": 3.686159982807524e-08,
    "international_organization_knowledge|WVS_E": 0.7931207753233521,
    "job_scarcity_gender_discrimination|WVS_C": 0.7740567848655293,
    "job_scarcity_nativist_preference|WVS_C": 0.7836203894479408,
    "life_autonomy_morality_permissiveness|WVS_F": 0.7939087901997979,
    "multilevel_place_attachment|WVS_G": 0.7898154653518278,
    "neighborhood_disorder_and_crime|WVS_H": 0.7698946796554332,
    "offline_political_participation|WVS_E": 3.686159985583082e-08,
    "online_political_participation|WVS_E": 3.686159985583082e-08,
    "outgroup_trust|WVS_G": 0.7868642372570598,
    "perceived_corruption|WVS_E": 0.7772220239722185,
    "perceived_negative_effects_of_immigration|WVS_G": 0.779024812656177,
    "perceived_positive_effects_of_immigration|WVS_G": 0.7860165628173733,
    "political_information_sources|WVS_E": 0.7656058682565486,
    "postmaterialist_values|WVS_E": 0.7950693458307189,
    "precautionary_security_behaviors|WVS_H": 0.78716538412297,
    "religion_versus_secularism_orientation|WVS_F": 0.7853145108198472,
    "religious_belief|WVS_F": 3.686159985583082e-08,
    "religious_exclusivism|WVS_F": 3.686159985583082e-08,
    "religious_practice_and_self_identification|WVS_F": 0.7808850686370976,
    "science_skepticism|WVS_I": 0.795666800328605,
    "science_technology_optimism|WVS_E": 0.7899540245942919,
    "sexual_and_reproductive_morality_permissiveness|WVS_F": 0.7846099704103122,
    "social_intolerance_outgroups|WVS_A": 0.7677753069436565,
    "societal_change_attitudes|WVS_E": 0.7896484564784563,
    "socioeconomic_insecurity_worry|WVS_H": 0.7741803431262793,
    "subjective_wellbeing|WVS_A": 0.7872891966558616,
    "violence_tolerance|WVS_F": 0.788547133277088,
    "voluntary_association_active_membership|WVS_A": 3.686159985583082e-08,
    "voluntary_association_belonging|WVS_A": 0.7761792414580152,
    "voting_participation|WVS_E": 0.7802107305728163,
    "work_ethic|WVS_C": 0.7919901274827513
  },
  "sink_scores": {
    "acceptance_of_state_surveillance|WVS_H": 0.4698298883037377,
    "authoritarian_governance_tolerance|WVS_E": 0.8049766237079095,
    "autocracy_support|WVS_E": 0.5004991498376936,
    "basic_needs_deprivation|WVS_H": 0.984198448043679,
    "child_qualities_autonomy_self_expression|WVS_A": 0.4672127385162079,
    "child_qualities_conformity_tradition|WVS_A": 0.6419972025829703,
    "child_qualities_prosocial_diligence|WVS_A": 0.5470060592283442,
    "civic_dishonesty_tolerance|WVS_F": 0.8835590494855191,
    "confidence_in_civil_society_organizations|WVS_E": 0.7034230220016563,
    "confidence_in_domestic_institutions|WVS_E": 0.9913026533998257,
    "confidence_in_international_organizations|WVS_E": 0.3325542037672492,
    "crime_victimization|WVS_H": 0.5473153241714117,
    "democratic_system_evaluation|WVS_E": 0.49356049639917465,
    "democratic_values_importance|WVS_E": 0.46497249592307965,
    "economic_ideology|WVS_E": 0.2539988206378106,
    "electoral_integrity|WVS_E": 0.5112089078563906,
    "existential_threat_worry|WVS_H": 0.0,
    "familial_duty_obligations|WVS_D": 1.4600532681365845,
    "female_income_threat_to_marriage|WVS_D": 0.8883650495061781,
    "freedom_security_tradeoff_perception|WVS_H": 0.6898871768922055,
    "gender_role_traditionalism|WVS_D": 1.5811609807313283,
    "immigrant_origin_status|WVS_G": 0.0,
    "importance_of_life_domains|WVS_A": 0.3979814153047106,
    "institutional_threat_perception|WVS_H": 0.0,
    "international_organization_knowledge|WVS_E": 0.3420714829365149,
    "job_scarcity_gender_discrimination|WVS_C": 1.4163400238569925,
    "job_scarcity_nativist_preference|WVS_C": 0.8807308984727569,
    "life_autonomy_morality_permissiveness|WVS_F": 0.31020221294778283,
    "multilevel_place_attachment|WVS_G": 0.5437424408181055,
    "neighborhood_disorder_and_crime|WVS_H": 1.6031167062416392,
    "offline_political_participation|WVS_E": 0.0,
    "online_political_participation|WVS_E": 0.0,
    "outgroup_trust|WVS_G": 0.6856986788581861,
    "perceived_corruption|WVS_E": 1.174037656129095,
    "perceived_negative_effects_of_immigration|WVS_G": 1.1278160198461298,
    "perceived_positive_effects_of_immigration|WVS_G": 0.7166405599321407,
    "political_information_sources|WVS_E": 1.7493318839866574,
    "postmaterialist_values|WVS_E": 0.25518054605361573,
    "precautionary_security_behaviors|WVS_H": 0.6551670102650046,
    "religion_versus_secularism_orientation|WVS_F": 0.7898505405118027,
    "religious_belief|WVS_F": 0.0,
    "religious_exclusivism|WVS_F": 0.0,
    "religious_practice_and_self_identification|WVS_F": 1.0285316371045126,
    "science_skepticism|WVS_I": 0.22516258882481202,
    "science_technology_optimism|WVS_E": 0.5060180736287737,
    "sexual_and_reproductive_morality_permissiveness|WVS_F": 0.8005228419832453,
    "social_intolerance_outgroups|WVS_A": 1.730385217169216,
    "societal_change_attitudes|WVS_E": 0.5178726714396569,
    "socioeconomic_insecurity_worry|WVS_H": 1.3702908268807104,
    "subjective_wellbeing|WVS_A": 0.6646729092078548,
    "violence_tolerance|WVS_F": 0.5985454230595693,
    "voluntary_association_active_membership|WVS_A": 0.0,
    "voluntary_association_belonging|WVS_A": 1.2120028800510294,
    "voting_participation|WVS_E": 0.9661249749724511,
    "work_ethic|WVS_C": 0.406193791363313
  },
  "hub_ranking": [
    {
      "rank": 1,
      "construct": "science_skepticism|WVS_I",
      "score": 0.795666800328605
    },
    {
      "rank": 2,
      "construct": "postmaterialist_values|WVS_E",
      "score": 0.7950693458307189
    },
    {
      "rank": 3,
      "construct": "economic_ideology|WVS_E",
      "score": 0.7942473249954501
    },
    {
      "rank": 4,
      "construct": "life_autonomy_morality_permissiveness|WVS_F",
      "score": 0.7939087901997979
    },
    {
      "rank": 5,
      "construct": "confidence_in_international_organizations|WVS_E",
      "score": 0.7932737026114282
    },
    {
      "rank": 6,
      "construct": "international_organization_knowledge|WVS_E",
      "score": 0.7931207753233521
    },
    {
      "rank": 7,
      "construct": "importance_of_life_domains|WVS_A",
      "score": 0.7924607893533282
    },
    {
      "rank": 8,
      "construct": "work_ethic|WVS_C",
      "score": 0.7919901274827513
    },
    {
      "rank": 9,
      "construct": "child_qualities_autonomy_self_expression|WVS_A",
      "score": 0.7911539784442909
    },
    {
      "rank": 10,
      "construct": "acceptance_of_state_surveillance|WVS_H",
      "score": 0.7907847367854333
    },
    {
      "rank": 11,
      "construct": "democratic_values_importance|WVS_E",
      "score": 0.7906630389435878
    },
    {
      "rank": 12,
      "construct": "science_technology_optimism|WVS_E",
      "score": 0.7899540245942919
    },
    {
      "rank": 13,
      "construct": "democratic_system_evaluation|WVS_E",
      "score": 0.7899452403559761
    },
    {
      "rank": 14,
      "construct": "autocracy_support|WVS_E",
      "score": 0.7899263451662377
    },
    {
      "rank": 15,
      "construct": "multilevel_place_attachment|WVS_G",
      "score": 0.7898154653518278
    },
    {
      "rank": 16,
      "construct": "societal_change_attitudes|WVS_E",
      "score": 0.7896484564784563
    },
    {
      "rank": 17,
      "construct": "electoral_integrity|WVS_E",
      "score": 0.7895711268794515
    },
    {
      "rank": 18,
      "construct": "child_qualities_prosocial_diligence|WVS_A",
      "score": 0.7888079459420545
    },
    {
      "rank": 19,
      "construct": "violence_tolerance|WVS_F",
      "score": 0.788547133277088
    },
    {
      "rank": 20,
      "construct": "crime_victimization|WVS_H",
      "score": 0.7883525274807842
    },
    {
      "rank": 21,
      "construct": "child_qualities_conformity_tradition|WVS_A",
      "score": 0.787931013784601
    },
    {
      "rank": 22,
      "construct": "subjective_wellbeing|WVS_A",
      "score": 0.7872891966558616
    },
    {
      "rank": 23,
      "construct": "precautionary_security_behaviors|WVS_H",
      "score": 0.78716538412297
    },
    {
      "rank": 24,
      "construct": "freedom_security_tradeoff_perception|WVS_H",
      "score": 0.7869220134475824
    },
    {
      "rank": 25,
      "construct": "outgroup_trust|WVS_G",
      "score": 0.7868642372570598
    },
    {
      "rank": 26,
      "construct": "perceived_positive_effects_of_immigration|WVS_G",
      "score": 0.7860165628173733
    },
    {
      "rank": 27,
      "construct": "confidence_in_civil_society_organizations|WVS_E",
      "score": 0.7859489032476935
    },
    {
      "rank": 28,
      "construct": "religion_versus_secularism_orientation|WVS_F",
      "score": 0.7853145108198472
    },
    {
      "rank": 29,
      "construct": "sexual_and_reproductive_morality_permissiveness|WVS_F",
      "score": 0.7846099704103122
    },
    {
      "rank": 30,
      "construct": "authoritarian_governance_tolerance|WVS_E",
      "score": 0.7843813172165961
    },
    {
      "rank": 31,
      "construct": "civic_dishonesty_tolerance|WVS_F",
      "score": 0.783658777474924
    },
    {
      "rank": 32,
      "construct": "job_scarcity_nativist_preference|WVS_C",
      "score": 0.7836203894479408
    },
    {
      "rank": 33,
      "construct": "female_income_threat_to_marriage|WVS_D",
      "score": 0.7834398377245073
    },
    {
      "rank": 34,
      "construct": "basic_needs_deprivation|WVS_H",
      "score": 0.7813581425203521
    },
    {
      "rank": 35,
      "construct": "religious_practice_and_self_identification|WVS_F",
      "score": 0.7808850686370976
    },
    {
      "rank": 36,
      "construct": "confidence_in_domestic_institutions|WVS_E",
      "score": 0.7806840148046206
    },
    {
      "rank": 37,
      "construct": "voting_participation|WVS_E",
      "score": 0.7802107305728163
    },
    {
      "rank": 38,
      "construct": "perceived_negative_effects_of_immigration|WVS_G",
      "score": 0.779024812656177
    },
    {
      "rank": 39,
      "construct": "perceived_corruption|WVS_E",
      "score": 0.7772220239722185
    },
    {
      "rank": 40,
      "construct": "voluntary_association_belonging|WVS_A",
      "score": 0.7761792414580152
    },
    {
      "rank": 41,
      "construct": "socioeconomic_insecurity_worry|WVS_H",
      "score": 0.7741803431262793
    },
    {
      "rank": 42,
      "construct": "job_scarcity_gender_discrimination|WVS_C",
      "score": 0.7740567848655293
    },
    {
      "rank": 43,
      "construct": "familial_duty_obligations|WVS_D",
      "score": 0.7734992874654286
    },
    {
      "rank": 44,
      "construct": "gender_role_traditionalism|WVS_D",
      "score": 0.7706670808960833
    },
    {
      "rank": 45,
      "construct": "neighborhood_disorder_and_crime|WVS_H",
      "score": 0.7698946796554332
    },
    {
      "rank": 46,
      "construct": "social_intolerance_outgroups|WVS_A",
      "score": 0.7677753069436565
    },
    {
      "rank": 47,
      "construct": "political_information_sources|WVS_E",
      "score": 0.7656058682565486
    },
    {
      "rank": 48,
      "construct": "voluntary_association_active_membership|WVS_A",
      "score": 3.686159985583082e-08
    },
    {
      "rank": 49,
      "construct": "existential_threat_worry|WVS_H",
      "score": 3.686159985583082e-08
    },
    {
      "rank": 50,
      "construct": "religious_belief|WVS_F",
      "score": 3.686159985583082e-08
    },
    {
      "rank": 51,
      "construct": "immigrant_origin_status|WVS_G",
      "score": 3.686159985583082e-08
    },
    {
      "rank": 52,
      "construct": "offline_political_participation|WVS_E",
      "score": 3.686159985583082e-08
    },
    {
      "rank": 53,
      "construct": "religious_exclusivism|WVS_F",
      "score": 3.686159985583082e-08
    },
    {
      "rank": 54,
      "construct": "online_political_participation|WVS_E",
      "score": 3.686159985583082e-08
    },
    {
      "rank": 55,
      "construct": "institutional_threat_perception|WVS_H",
      "score": 3.686159982807524e-08
    }
  ],
  "sink_ranking": [
    {
      "rank": 1,
      "construct": "political_information_sources|WVS_E",
      "score": 1.7493318839866574
    },
    {
      "rank": 2,
      "construct": "social_intolerance_outgroups|WVS_A",
      "score": 1.730385217169216
    },
    {
      "rank": 3,
      "construct": "neighborhood_disorder_and_crime|WVS_H",
      "score": 1.6031167062416392
    },
    {
      "rank": 4,
      "construct": "gender_role_traditionalism|WVS_D",
      "score": 1.5811609807313283
    },
    {
      "rank": 5,
      "construct": "familial_duty_obligations|WVS_D",
      "score": 1.4600532681365845
    },
    {
      "rank": 6,
      "construct": "job_scarcity_gender_discrimination|WVS_C",
      "score": 1.4163400238569925
    },
    {
      "rank": 7,
      "construct": "socioeconomic_insecurity_worry|WVS_H",
      "score": 1.3702908268807104
    },
    {
      "rank": 8,
      "construct": "voluntary_association_belonging|WVS_A",
      "score": 1.2120028800510294
    },
    {
      "rank": 9,
      "construct": "perceived_corruption|WVS_E",
      "score": 1.174037656129095
    },
    {
      "rank": 10,
      "construct": "perceived_negative_effects_of_immigration|WVS_G",
      "score": 1.1278160198461298
    },
    {
      "rank": 11,
      "construct": "religious_practice_and_self_identification|WVS_F",
      "score": 1.0285316371045126
    },
    {
      "rank": 12,
      "construct": "confidence_in_domestic_institutions|WVS_E",
      "score": 0.9913026533998257
    },
    {
      "rank": 13,
      "construct": "basic_needs_deprivation|WVS_H",
      "score": 0.984198448043679
    },
    {
      "rank": 14,
      "construct": "voting_participation|WVS_E",
      "score": 0.9661249749724511
    },
    {
      "rank": 15,
      "construct": "female_income_threat_to_marriage|WVS_D",
      "score": 0.8883650495061781
    },
    {
      "rank": 16,
      "construct": "civic_dishonesty_tolerance|WVS_F",
      "score": 0.8835590494855191
    },
    {
      "rank": 17,
      "construct": "job_scarcity_nativist_preference|WVS_C",
      "score": 0.8807308984727569
    },
    {
      "rank": 18,
      "construct": "authoritarian_governance_tolerance|WVS_E",
      "score": 0.8049766237079095
    },
    {
      "rank": 19,
      "construct": "sexual_and_reproductive_morality_permissiveness|WVS_F",
      "score": 0.8005228419832453
    },
    {
      "rank": 20,
      "construct": "religion_versus_secularism_orientation|WVS_F",
      "score": 0.7898505405118027
    },
    {
      "rank": 21,
      "construct": "perceived_positive_effects_of_immigration|WVS_G",
      "score": 0.7166405599321407
    },
    {
      "rank": 22,
      "construct": "confidence_in_civil_society_organizations|WVS_E",
      "score": 0.7034230220016563
    },
    {
      "rank": 23,
      "construct": "freedom_security_tradeoff_perception|WVS_H",
      "score": 0.6898871768922055
    },
    {
      "rank": 24,
      "construct": "outgroup_trust|WVS_G",
      "score": 0.6856986788581861
    },
    {
      "rank": 25,
      "construct": "subjective_wellbeing|WVS_A",
      "score": 0.6646729092078548
    },
    {
      "rank": 26,
      "construct": "precautionary_security_behaviors|WVS_H",
      "score": 0.6551670102650046
    },
    {
      "rank": 27,
      "construct": "child_qualities_conformity_tradition|WVS_A",
      "score": 0.6419972025829703
    },
    {
      "rank": 28,
      "construct": "violence_tolerance|WVS_F",
      "score": 0.5985454230595693
    },
    {
      "rank": 29,
      "construct": "crime_victimization|WVS_H",
      "score": 0.5473153241714117
    },
    {
      "rank": 30,
      "construct": "child_qualities_prosocial_diligence|WVS_A",
      "score": 0.5470060592283442
    },
    {
      "rank": 31,
      "construct": "multilevel_place_attachment|WVS_G",
      "score": 0.5437424408181055
    },
    {
      "rank": 32,
      "construct": "societal_change_attitudes|WVS_E",
      "score": 0.5178726714396569
    },
    {
      "rank": 33,
      "construct": "electoral_integrity|WVS_E",
      "score": 0.5112089078563906
    },
    {
      "rank": 34,
      "construct": "science_technology_optimism|WVS_E",
      "score": 0.5060180736287737
    },
    {
      "rank": 35,
      "construct": "autocracy_support|WVS_E",
      "score": 0.5004991498376936
    },
    {
      "rank": 36,
      "construct": "democratic_system_evaluation|WVS_E",
      "score": 0.49356049639917465
    },
    {
      "rank": 37,
      "construct": "acceptance_of_state_surveillance|WVS_H",
      "score": 0.4698298883037377
    },
    {
      "rank": 38,
      "construct": "child_qualities_autonomy_self_expression|WVS_A",
      "score": 0.4672127385162079
    },
    {
      "rank": 39,
      "construct": "democratic_values_importance|WVS_E",
      "score": 0.46497249592307965
    },
    {
      "rank": 40,
      "construct": "work_ethic|WVS_C",
      "score": 0.406193791363313
    },
    {
      "rank": 41,
      "construct": "importance_of_life_domains|WVS_A",
      "score": 0.3979814153047106
    },
    {
      "rank": 42,
      "construct": "international_organization_knowledge|WVS_E",
      "score": 0.3420714829365149
    },
    {
      "rank": 43,
      "construct": "confidence_in_international_organizations|WVS_E",
      "score": 0.3325542037672492
    },
    {
      "rank": 44,
      "construct": "life_autonomy_morality_permissiveness|WVS_F",
      "score": 0.31020221294778283
    },
    {
      "rank": 45,
      "construct": "postmaterialist_values|WVS_E",
      "score": 0.25518054605361573
    },
    {
      "rank": 46,
      "construct": "economic_ideology|WVS_E",
      "score": 0.2539988206378106
    },
    {
      "rank": 47,
      "construct": "science_skepticism|WVS_I",
      "score": 0.22516258882481202
    },
    {
      "rank": 48,
      "construct": "religious_belief|WVS_F",
      "score": 0.0
    },
    {
      "rank": 49,
      "construct": "religious_exclusivism|WVS_F",
      "score": 0.0
    },
    {
      "rank": 50,
      "construct": "online_political_participation|WVS_E",
      "score": 0.0
    },
    {
      "rank": 51,
      "construct": "offline_political_participation|WVS_E",
      "score": 0.0
    },
    {
      "rank": 52,
      "construct": "institutional_threat_perception|WVS_H",
      "score": 0.0
    },
    {
      "rank": 53,
      "construct": "immigrant_origin_status|WVS_G",
      "score": 0.0
    },
    {
      "rank": 54,
      "construct": "existential_threat_worry|WVS_H",
      "score": 0.0
    },
    {
      "rank": 55,
      "construct": "voluntary_association_active_membership|WVS_A",
      "score": 0.0
    }
  ],
  "top_asymmetric_pairs": [
    {
      "source": "confidence_in_international_organizations|WVS_E",
      "target": "social_intolerance_outgroups|WVS_A",
      "asymmetry": 0.03522405645216925
    },
    {
      "source": "postmaterialist_values|WVS_E",
      "target": "social_intolerance_outgroups|WVS_A",
      "asymmetry": 0.0350774755377961
    },
    {
      "source": "economic_ideology|WVS_E",
      "target": "voluntary_association_belonging|WVS_A",
      "asymmetry": 0.03480905087459418
    },
    {
      "source": "importance_of_life_domains|WVS_A",
      "target": "political_information_sources|WVS_E",
      "asymmetry": 0.03458358193532943
    },
    {
      "source": "life_autonomy_morality_permissiveness|WVS_F",
      "target": "social_intolerance_outgroups|WVS_A",
      "asymmetry": 0.03435693194183765
    },
    {
      "source": "economic_ideology|WVS_E",
      "target": "socioeconomic_insecurity_worry|WVS_H",
      "asymmetry": 0.03399526533920859
    },
    {
      "source": "postmaterialist_values|WVS_E",
      "target": "gender_role_traditionalism|WVS_D",
      "asymmetry": 0.03228478000752219
    },
    {
      "source": "life_autonomy_morality_permissiveness|WVS_F",
      "target": "political_information_sources|WVS_E",
      "asymmetry": 0.032224881888652135
    },
    {
      "source": "life_autonomy_morality_permissiveness|WVS_F",
      "target": "neighborhood_disorder_and_crime|WVS_H",
      "asymmetry": 0.03213485424456628
    },
    {
      "source": "democratic_values_importance|WVS_E",
      "target": "social_intolerance_outgroups|WVS_A",
      "asymmetry": 0.03132738833714331
    },
    {
      "source": "work_ethic|WVS_C",
      "target": "political_information_sources|WVS_E",
      "asymmetry": 0.031305014289005596
    },
    {
      "source": "science_technology_optimism|WVS_E",
      "target": "social_intolerance_outgroups|WVS_A",
      "asymmetry": 0.031005924060282603
    },
    {
      "source": "international_organization_knowledge|WVS_E",
      "target": "neighborhood_disorder_and_crime|WVS_H",
      "asymmetry": 0.03082469732645294
    },
    {
      "source": "importance_of_life_domains|WVS_A",
      "target": "neighborhood_disorder_and_crime|WVS_H",
      "asymmetry": 0.030791954770806207
    },
    {
      "source": "science_skepticism|WVS_I",
      "target": "social_intolerance_outgroups|WVS_A",
      "asymmetry": 0.03041743059038725
    },
    {
      "source": "confidence_in_international_organizations|WVS_E",
      "target": "neighborhood_disorder_and_crime|WVS_H",
      "asymmetry": 0.03027481494509515
    },
    {
      "source": "postmaterialist_values|WVS_E",
      "target": "familial_duty_obligations|WVS_D",
      "asymmetry": 0.03015148607959809
    },
    {
      "source": "science_skepticism|WVS_I",
      "target": "neighborhood_disorder_and_crime|WVS_H",
      "asymmetry": 0.030136574068448708
    },
    {
      "source": "international_organization_knowledge|WVS_E",
      "target": "social_intolerance_outgroups|WVS_A",
      "asymmetry": 0.029445479693137905
    },
    {
      "source": "science_technology_optimism|WVS_E",
      "target": "neighborhood_disorder_and_crime|WVS_H",
      "asymmetry": 0.029409560699059083
    }
  ],
  "scenario": {
    "seed": "science_skepticism|WVS_I",
    "magnitude": 1.0,
    "shifts": [
      {
        "construct": "neighborhood_disorder_and_crime|WVS_H",
        "shift": 0.034802833200542435
      },
      {
        "construct": "social_intolerance_outgroups|WVS_A",
        "shift": 0.03468227161323889
      },
      {
        "construct": "voluntary_association_belonging|WVS_A",
        "shift": 0.033677947224082065
      },
      {
        "construct": "socioeconomic_insecurity_worry|WVS_H",
        "shift": 0.03157466739128579
      },
      {
        "construct": "political_information_sources|WVS_E",
        "shift": 0.0307807169900442
      },
      {
        "construct": "gender_role_traditionalism|WVS_D",
        "shift": 0.028348366262202704
      },
      {
        "construct": "familial_duty_obligations|WVS_D",
        "shift": 0.027576179025627326
      },
      {
        "construct": "perceived_corruption|WVS_E",
        "shift": 0.02645029992373595
      },
      {
        "construct": "job_scarcity_gender_discrimination|WVS_C",
        "shift": 0.02622341635418591
      },
      {
        "construct": "voting_participation|WVS_E",
        "shift": 0.02418918366434325
      },
      {
        "construct": "religious_practice_and_self_identification|WVS_F",
        "shift": 0.02418775834500938
      },
      {
        "construct": "perceived_negative_effects_of_immigration|WVS_G",
        "shift": 0.023886229215850943
      },
      {
        "construct": "female_income_threat_to_marriage|WVS_D",
        "shift": 0.020773883313153135
      },
      {
        "construct": "confidence_in_domestic_institutions|WVS_E",
        "shift": 0.020573569764265505
      },
      {
        "construct": "basic_needs_deprivation|WVS_H",
        "shift": 0.02041282211685781
      },
      {
        "construct": "authoritarian_governance_tolerance|WVS_E",
        "shift": 0.01840160956704861
      },
      {
        "construct": "outgroup_trust|WVS_G",
        "shift": 0.017191957582207058
      },
      {
        "construct": "job_scarcity_nativist_preference|WVS_C",
        "shift": 0.017050157495556547
      },
      {
        "construct": "democratic_system_evaluation|WVS_E",
        "shift": 0.01702385166275164
      },
      {
        "construct": "confidence_in_civil_society_organizations|WVS_E",
        "shift": 0.01645060395027486
      }
    ]
  },
  "mediator_correlation": {
    "spearman_rho": 0.0658227932475946,
    "p_value": 0.6330339546232466,
    "n_matched": 55,
    "interpretation": "weak agreement \u2014 PPR and mediator capture different aspects"
  },
  "alpha_sensitivity": {
    "per_alpha": {
      "0.10": [
        "science_skepticism|WVS_I",
        "postmaterialist_values|WVS_E",
        "economic_ideology|WVS_E",
        "life_autonomy_morality_permissiveness|WVS_F",
        "confidence_in_international_organizations|WVS_E",
        "international_organization_knowledge|WVS_E",
        "importance_of_life_domains|WVS_A",
        "work_ethic|WVS_C",
        "child_qualities_autonomy_self_expression|WVS_A",
        "acceptance_of_state_surveillance|WVS_H",
        "democratic_values_importance|WVS_E",
        "democratic_system_evaluation|WVS_E",
        "autocracy_support|WVS_E",
        "science_technology_optimism|WVS_E",
        "electoral_integrity|WVS_E",
        "societal_change_attitudes|WVS_E",
        "multilevel_place_attachment|WVS_G",
        "child_qualities_prosocial_diligence|WVS_A",
        "crime_victimization|WVS_H",
        "violence_tolerance|WVS_F",
        "child_qualities_conformity_tradition|WVS_A",
        "precautionary_security_behaviors|WVS_H",
        "subjective_wellbeing|WVS_A",
        "outgroup_trust|WVS_G",
        "freedom_security_tradeoff_perception|WVS_H",
        "perceived_positive_effects_of_immigration|WVS_G",
        "confidence_in_civil_society_organizations|WVS_E",
        "religion_versus_secularism_orientation|WVS_F",
        "sexual_and_reproductive_morality_permissiveness|WVS_F",
        "authoritarian_governance_tolerance|WVS_E",
        "civic_dishonesty_tolerance|WVS_F",
        "female_income_threat_to_marriage|WVS_D",
        "job_scarcity_nativist_preference|WVS_C",
        "basic_needs_deprivation|WVS_H",
        "voting_participation|WVS_E",
        "religious_practice_and_self_identification|WVS_F",
        "confidence_in_domestic_institutions|WVS_E",
        "perceived_negative_effects_of_immigration|WVS_G",
        "perceived_corruption|WVS_E",
        "voluntary_association_belonging|WVS_A",
        "socioeconomic_insecurity_worry|WVS_H",
        "job_scarcity_gender_discrimination|WVS_C",
        "familial_duty_obligations|WVS_D",
        "gender_role_traditionalism|WVS_D",
        "neighborhood_disorder_and_crime|WVS_H",
        "social_intolerance_outgroups|WVS_A",
        "political_information_sources|WVS_E",
        "voluntary_association_active_membership|WVS_A",
        "existential_threat_worry|WVS_H",
        "religious_belief|WVS_F",
        "religious_exclusivism|WVS_F",
        "immigrant_origin_status|WVS_G",
        "institutional_threat_perception|WVS_H",
        "offline_political_participation|WVS_E",
        "online_political_participation|WVS_E"
      ],
      "0.15": [
        "science_skepticism|WVS_I",
        "postmaterialist_values|WVS_E",
        "economic_ideology|WVS_E",
        "life_autonomy_morality_permissiveness|WVS_F",
        "confidence_in_international_organizations|WVS_E",
        "international_organization_knowledge|WVS_E",
        "importance_of_life_domains|WVS_A",
        "work_ethic|WVS_C",
        "child_qualities_autonomy_self_expression|WVS_A",
        "acceptance_of_state_surveillance|WVS_H",
        "democratic_values_importance|WVS_E",
        "democratic_system_evaluation|WVS_E",
        "autocracy_support|WVS_E",
        "science_technology_optimism|WVS_E",
        "multilevel_place_attachment|WVS_G",
        "electoral_integrity|WVS_E",
        "societal_change_attitudes|WVS_E",
        "child_qualities_prosocial_diligence|WVS_A",
        "crime_victimization|WVS_H",
        "violence_tolerance|WVS_F",
        "child_qualities_conformity_tradition|WVS_A",
        "subjective_wellbeing|WVS_A",
        "precautionary_security_behaviors|WVS_H",
        "outgroup_trust|WVS_G",
        "freedom_security_tradeoff_perception|WVS_H",
        "perceived_positive_effects_of_immigration|WVS_G",
        "confidence_in_civil_society_organizations|WVS_E",
        "religion_versus_secularism_orientation|WVS_F",
        "sexual_and_reproductive_morality_permissiveness|WVS_F",
        "authoritarian_governance_tolerance|WVS_E",
        "civic_dishonesty_tolerance|WVS_F",
        "job_scarcity_nativist_preference|WVS_C",
        "female_income_threat_to_marriage|WVS_D",
        "basic_needs_deprivation|WVS_H",
        "religious_practice_and_self_identification|WVS_F",
        "confidence_in_domestic_institutions|WVS_E",
        "voting_participation|WVS_E",
        "perceived_negative_effects_of_immigration|WVS_G",
        "perceived_corruption|WVS_E",
        "voluntary_association_belonging|WVS_A",
        "socioeconomic_insecurity_worry|WVS_H",
        "job_scarcity_gender_discrimination|WVS_C",
        "familial_duty_obligations|WVS_D",
        "gender_role_traditionalism|WVS_D",
        "neighborhood_disorder_and_crime|WVS_H",
        "social_intolerance_outgroups|WVS_A",
        "political_information_sources|WVS_E",
        "immigrant_origin_status|WVS_G",
        "existential_threat_worry|WVS_H",
        "institutional_threat_perception|WVS_H",
        "voluntary_association_active_membership|WVS_A",
        "religious_belief|WVS_F",
        "offline_political_participation|WVS_E",
        "religious_exclusivism|WVS_F",
        "online_political_participation|WVS_E"
      ],
      "0.20": [
        "science_skepticism|WVS_I",
        "postmaterialist_values|WVS_E",
        "economic_ideology|WVS_E",
        "life_autonomy_morality_permissiveness|WVS_F",
        "confidence_in_international_organizations|WVS_E",
        "international_organization_knowledge|WVS_E",
        "importance_of_life_domains|WVS_A",
        "work_ethic|WVS_C",
        "child_qualities_autonomy_self_expression|WVS_A",
        "acceptance_of_state_surveillance|WVS_H",
        "democratic_values_importance|WVS_E",
        "science_technology_optimism|WVS_E",
        "democratic_system_evaluation|WVS_E",
        "autocracy_support|WVS_E",
        "multilevel_place_attachment|WVS_G",
        "societal_change_attitudes|WVS_E",
        "electoral_integrity|WVS_E",
        "child_qualities_prosocial_diligence|WVS_A",
        "violence_tolerance|WVS_F",
        "crime_victimization|WVS_H",
        "child_qualities_conformity_tradition|WVS_A",
        "subjective_wellbeing|WVS_A",
        "precautionary_security_behaviors|WVS_H",
        "freedom_security_tradeoff_perception|WVS_H",
        "outgroup_trust|WVS_G",
        "perceived_positive_effects_of_immigration|WVS_G",
        "confidence_in_civil_society_organizations|WVS_E",
        "religion_versus_secularism_orientation|WVS_F",
        "sexual_and_reproductive_morality_permissiveness|WVS_F",
        "authoritarian_governance_tolerance|WVS_E",
        "civic_dishonesty_tolerance|WVS_F",
        "job_scarcity_nativist_preference|WVS_C",
        "female_income_threat_to_marriage|WVS_D",
        "basic_needs_deprivation|WVS_H",
        "religious_practice_and_self_identification|WVS_F",
        "confidence_in_domestic_institutions|WVS_E",
        "voting_participation|WVS_E",
        "perceived_negative_effects_of_immigration|WVS_G",
        "perceived_corruption|WVS_E",
        "voluntary_association_belonging|WVS_A",
        "socioeconomic_insecurity_worry|WVS_H",
        "job_scarcity_gender_discrimination|WVS_C",
        "familial_duty_obligations|WVS_D",
        "gender_role_traditionalism|WVS_D",
        "neighborhood_disorder_and_crime|WVS_H",
        "social_intolerance_outgroups|WVS_A",
        "political_information_sources|WVS_E",
        "voluntary_association_active_membership|WVS_A",
        "existential_threat_worry|WVS_H",
        "religious_belief|WVS_F",
        "immigrant_origin_status|WVS_G",
        "offline_political_participation|WVS_E",
        "religious_exclusivism|WVS_F",
        "online_political_participation|WVS_E",
        "institutional_threat_perception|WVS_H"
      ],
      "0.30": [
        "science_skepticism|WVS_I",
        "postmaterialist_values|WVS_E",
        "economic_ideology|WVS_E",
        "life_autonomy_morality_permissiveness|WVS_F",
        "confidence_in_international_organizations|WVS_E",
        "international_organization_knowledge|WVS_E",
        "importance_of_life_domains|WVS_A",
        "work_ethic|WVS_C",
        "child_qualities_autonomy_self_expression|WVS_A",
        "democratic_values_importance|WVS_E",
        "acceptance_of_state_surveillance|WVS_H",
        "science_technology_optimism|WVS_E",
        "multilevel_place_attachment|WVS_G",
        "autocracy_support|WVS_E",
        "democratic_system_evaluation|WVS_E",
        "societal_change_attitudes|WVS_E",
        "electoral_integrity|WVS_E",
        "violence_tolerance|WVS_F",
        "child_qualities_prosocial_diligence|WVS_A",
        "child_qualities_conformity_tradition|WVS_A",
        "crime_victimization|WVS_H",
        "subjective_wellbeing|WVS_A",
        "precautionary_security_behaviors|WVS_H",
        "freedom_security_tradeoff_perception|WVS_H",
        "outgroup_trust|WVS_G",
        "perceived_positive_effects_of_immigration|WVS_G",
        "confidence_in_civil_society_organizations|WVS_E",
        "religion_versus_secularism_orientation|WVS_F",
        "sexual_and_reproductive_morality_permissiveness|WVS_F",
        "authoritarian_governance_tolerance|WVS_E",
        "civic_dishonesty_tolerance|WVS_F",
        "job_scarcity_nativist_preference|WVS_C",
        "female_income_threat_to_marriage|WVS_D",
        "basic_needs_deprivation|WVS_H",
        "religious_practice_and_self_identification|WVS_F",
        "confidence_in_domestic_institutions|WVS_E",
        "voting_participation|WVS_E",
        "perceived_negative_effects_of_immigration|WVS_G",
        "perceived_corruption|WVS_E",
        "voluntary_association_belonging|WVS_A",
        "job_scarcity_gender_discrimination|WVS_C",
        "socioeconomic_insecurity_worry|WVS_H",
        "familial_duty_obligations|WVS_D",
        "gender_role_traditionalism|WVS_D",
        "neighborhood_disorder_and_crime|WVS_H",
        "social_intolerance_outgroups|WVS_A",
        "political_information_sources|WVS_E",
        "religious_belief|WVS_F",
        "religious_exclusivism|WVS_F",
        "existential_threat_worry|WVS_H",
        "institutional_threat_perception|WVS_H",
        "offline_political_participation|WVS_E",
        "online_political_participation|WVS_E",
        "immigrant_origin_status|WVS_G",
        "voluntary_association_active_membership|WVS_A"
      ],
      "0.50": [
        "science_skepticism|WVS_I",
        "postmaterialist_values|WVS_E",
        "life_autonomy_morality_permissiveness|WVS_F",
        "economic_ideology|WVS_E",
        "confidence_in_international_organizations|WVS_E",
        "importance_of_life_domains|WVS_A",
        "international_organization_knowledge|WVS_E",
        "work_ethic|WVS_C",
        "child_qualities_autonomy_self_expression|WVS_A",
        "democratic_values_importance|WVS_E",
        "acceptance_of_state_surveillance|WVS_H",
        "multilevel_place_attachment|WVS_G",
        "science_technology_optimism|WVS_E",
        "autocracy_support|WVS_E",
        "democratic_system_evaluation|WVS_E",
        "societal_change_attitudes|WVS_E",
        "electoral_integrity|WVS_E",
        "violence_tolerance|WVS_F",
        "child_qualities_conformity_tradition|WVS_A",
        "child_qualities_prosocial_diligence|WVS_A",
        "subjective_wellbeing|WVS_A",
        "freedom_security_tradeoff_perception|WVS_H",
        "precautionary_security_behaviors|WVS_H",
        "crime_victimization|WVS_H",
        "outgroup_trust|WVS_G",
        "religion_versus_secularism_orientation|WVS_F",
        "perceived_positive_effects_of_immigration|WVS_G",
        "confidence_in_civil_society_organizations|WVS_E",
        "sexual_and_reproductive_morality_permissiveness|WVS_F",
        "job_scarcity_nativist_preference|WVS_C",
        "civic_dishonesty_tolerance|WVS_F",
        "authoritarian_governance_tolerance|WVS_E",
        "female_income_threat_to_marriage|WVS_D",
        "basic_needs_deprivation|WVS_H",
        "religious_practice_and_self_identification|WVS_F",
        "confidence_in_domestic_institutions|WVS_E",
        "perceived_negative_effects_of_immigration|WVS_G",
        "voting_participation|WVS_E",
        "perceived_corruption|WVS_E",
        "job_scarcity_gender_discrimination|WVS_C",
        "familial_duty_obligations|WVS_D",
        "voluntary_association_belonging|WVS_A",
        "socioeconomic_insecurity_worry|WVS_H",
        "gender_role_traditionalism|WVS_D",
        "neighborhood_disorder_and_crime|WVS_H",
        "social_intolerance_outgroups|WVS_A",
        "political_information_sources|WVS_E",
        "institutional_threat_perception|WVS_H",
        "immigrant_origin_status|WVS_G",
        "voluntary_association_active_membership|WVS_A",
        "religious_exclusivism|WVS_F",
        "religious_belief|WVS_F",
        "offline_political_participation|WVS_E",
        "existential_threat_worry|WVS_H",
        "online_political_participation|WVS_E"
      ]
    },
    "stable_hubs": [
      "child_qualities_autonomy_self_expression|WVS_A",
      "confidence_in_international_organizations|WVS_E",
      "economic_ideology|WVS_E",
      "importance_of_life_domains|WVS_A",
      "international_organization_knowledge|WVS_E",
      "life_autonomy_morality_permissiveness|WVS_F",
      "postmaterialist_values|WVS_E",
      "science_skepticism|WVS_I",
      "work_ethic|WVS_C"
    ],
    "sensitive_constructs": []
  }
}