{
  "country": "TJK",
  "alpha": 0.2,
  "n_constructs": 55,
  "hub_scores": {
    "acceptance_of_state_surveillance|WVS_H": 0.7859719488720732,
    "authoritarian_governance_tolerance|WVS_E": 0.7888344515779869,
    "autocracy_support|WVS_E": 0.7797921094444039,
    "basic_needs_deprivation|WVS_H": 0.7938855061664691,
    "child_qualities_autonomy_self_expression|WVS_A": 0.7915567612291134,
    "child_qualities_conformity_tradition|WVS_A": 0.7948626858651908,
    "child_qualities_prosocial_diligence|WVS_A": 0.7951178345768104,
    "civic_dishonesty_tolerance|WVS_F": 0.7881879576865941,
    "confidence_in_civil_society_organizations|WVS_E": 0.7972234754431002,
    "confidence_in_domestic_institutions|WVS_E": 0.7957858788935752,
    "confidence_in_international_organizations|WVS_E": 0.7943035643988285,
    "crime_victimization|WVS_H": 0.7819016747413483,
    "democratic_system_evaluation|WVS_E": 0.7959341971207795,
    "democratic_values_importance|WVS_E": 0.7886716654769989,
    "economic_ideology|WVS_E": 0.796186689203697,
    "electoral_integrity|WVS_E": 0.7949118997295764,
    "existential_threat_worry|WVS_H": 0.786208877399664,
    "familial_duty_obligations|WVS_D": 0.7895052487983618,
    "female_income_threat_to_marriage|WVS_D": 0.7877827396569949,
    "freedom_security_tradeoff_perception|WVS_H": 0.7947023122144848,
    "gender_role_traditionalism|WVS_D": 0.7886896742006353,
    "immigrant_origin_status|WVS_G": 0.7601780451208611,
    "importance_of_life_domains|WVS_A": 0.7920838012538922,
    "institutional_threat_perception|WVS_H": 3.325386879748926e-08,
    "international_organization_knowledge|WVS_E": 0.7869689996166872,
    "job_scarcity_gender_discrimination|WVS_C": 0.7827809731568648,
    "job_scarcity_nativist_preference|WVS_C": 0.7758747348530812,
    "life_autonomy_morality_permissiveness|WVS_F": 0.7773469563809076,
    "multilevel_place_attachment|WVS_G": 0.7964494400440854,
    "neighborhood_disorder_and_crime|WVS_H": 0.7867284045148775,
    "offline_political_participation|WVS_E": 3.3253868769733685e-08,
    "online_political_participation|WVS_E": 0.7735635690238043,
    "outgroup_trust|WVS_G": 0.7922989175499726,
    "perceived_corruption|WVS_E": 0.7859742327072543,
    "perceived_negative_effects_of_immigration|WVS_G": 0.7832380581529996,
    "perceived_positive_effects_of_immigration|WVS_G": 0.7894801817776359,
    "political_information_sources|WVS_E": 0.7878565412035278,
    "postmaterialist_values|WVS_E": 0.7941088449452111,
    "precautionary_security_behaviors|WVS_H": 0.7902369410838029,
    "religion_versus_secularism_orientation|WVS_F": 0.7784022218493228,
    "religious_belief|WVS_F": 0.7858077204655962,
    "religious_exclusivism|WVS_F": 0.7753997590394521,
    "religious_practice_and_self_identification|WVS_F": 0.7780820475837961,
    "science_skepticism|WVS_I": 0.7843538472869336,
    "science_technology_optimism|WVS_E": 0.7885945527468761,
    "sexual_and_reproductive_morality_permissiveness|WVS_F": 0.7765865090458082,
    "social_intolerance_outgroups|WVS_A": 0.7788459204062287,
    "societal_change_attitudes|WVS_E": 0.790727125326988,
    "socioeconomic_insecurity_worry|WVS_H": 0.7748310521727764,
    "subjective_wellbeing|WVS_A": 0.7939226883553602,
    "violence_tolerance|WVS_F": 0.7766555904472257,
    "voluntary_association_active_membership|WVS_A": 0.7843436693855536,
    "voluntary_association_belonging|WVS_A": 0.7819447935041812,
    "voting_participation|WVS_E": 0.7799546557032047,
    "work_ethic|WVS_C": 0.7897410012520846
  },
  "sink_scores": {
    "acceptance_of_state_surveillance|WVS_H": 0.8105284027864543,
    "authoritarian_governance_tolerance|WVS_E": 0.6314468338095569,
    "autocracy_support|WVS_E": 1.1238475868971438,
    "basic_needs_deprivation|WVS_H": 0.3575236376244275,
    "child_qualities_autonomy_self_expression|WVS_A": 0.4906914358255345,
    "child_qualities_conformity_tradition|WVS_A": 0.30341538537907115,
    "child_qualities_prosocial_diligence|WVS_A": 0.2896334089365216,
    "civic_dishonesty_tolerance|WVS_F": 0.7008995364562073,
    "confidence_in_civil_society_organizations|WVS_E": 0.15302402530011563,
    "confidence_in_domestic_institutions|WVS_E": 0.24063048448458346,
    "confidence_in_international_organizations|WVS_E": 0.31424251138935094,
    "crime_victimization|WVS_H": 1.0661801520732095,
    "democratic_system_evaluation|WVS_E": 0.20408186350018076,
    "democratic_values_importance|WVS_E": 0.6467925478124646,
    "economic_ideology|WVS_E": 0.21016363705318078,
    "electoral_integrity|WVS_E": 0.27885948143451733,
    "existential_threat_worry|WVS_H": 0.824925107810039,
    "familial_duty_obligations|WVS_D": 0.6079089425972547,
    "female_income_threat_to_marriage|WVS_D": 0.7404052309345093,
    "freedom_security_tradeoff_perception|WVS_H": 0.31580818537430866,
    "gender_role_traditionalism|WVS_D": 0.6733811850584052,
    "immigrant_origin_status|WVS_G": 2.3351677632343057,
    "importance_of_life_domains|WVS_A": 0.4469771686899413,
    "institutional_threat_perception|WVS_H": 0.0,
    "international_organization_knowledge|WVS_E": 0.706213716422917,
    "job_scarcity_gender_discrimination|WVS_C": 1.0084585297020046,
    "job_scarcity_nativist_preference|WVS_C": 1.460158212303784,
    "life_autonomy_morality_permissiveness|WVS_F": 1.354298500215865,
    "multilevel_place_attachment|WVS_G": 0.20444623174989762,
    "neighborhood_disorder_and_crime|WVS_H": 0.7742346117298513,
    "offline_political_participation|WVS_E": 0.0,
    "online_political_participation|WVS_E": 1.4859541343826508,
    "outgroup_trust|WVS_G": 0.45333442226322435,
    "perceived_corruption|WVS_E": 0.7971109986593704,
    "perceived_negative_effects_of_immigration|WVS_G": 0.9853966773721488,
    "perceived_positive_effects_of_immigration|WVS_G": 0.6118663178113696,
    "political_information_sources|WVS_E": 0.6731038925877908,
    "postmaterialist_values|WVS_E": 0.3379442923296574,
    "precautionary_security_behaviors|WVS_H": 0.5782820989670191,
    "religion_versus_secularism_orientation|WVS_F": 1.2946596635274594,
    "religious_belief|WVS_F": 0.817633594124346,
    "religious_exclusivism|WVS_F": 1.4337944153820743,
    "religious_practice_and_self_identification|WVS_F": 1.3019681475213631,
    "science_skepticism|WVS_I": 0.9305030689880527,
    "science_technology_optimism|WVS_E": 0.658237911771612,
    "sexual_and_reproductive_morality_permissiveness|WVS_F": 1.3801897295598702,
    "social_intolerance_outgroups|WVS_A": 1.2621174034409157,
    "societal_change_attitudes|WVS_E": 0.5242850098693022,
    "socioeconomic_insecurity_worry|WVS_H": 1.4797797513153612,
    "subjective_wellbeing|WVS_A": 0.35251913893528186,
    "violence_tolerance|WVS_F": 1.3850166248245477,
    "voluntary_association_active_membership|WVS_A": 0.8941392224576623,
    "voluntary_association_belonging|WVS_A": 1.0493436643345384,
    "voting_participation|WVS_E": 1.1019570076896403,
    "work_ethic|WVS_C": 0.6198975104604146
  },
  "hub_ranking": [
    {
      "rank": 1,
      "construct": "confidence_in_civil_society_organizations|WVS_E",
      "score": 0.7972234754431002
    },
    {
      "rank": 2,
      "construct": "multilevel_place_attachment|WVS_G",
      "score": 0.7964494400440854
    },
    {
      "rank": 3,
      "construct": "economic_ideology|WVS_E",
      "score": 0.796186689203697
    },
    {
      "rank": 4,
      "construct": "democratic_system_evaluation|WVS_E",
      "score": 0.7959341971207795
    },
    {
      "rank": 5,
      "construct": "confidence_in_domestic_institutions|WVS_E",
      "score": 0.7957858788935752
    },
    {
      "rank": 6,
      "construct": "child_qualities_prosocial_diligence|WVS_A",
      "score": 0.7951178345768104
    },
    {
      "rank": 7,
      "construct": "electoral_integrity|WVS_E",
      "score": 0.7949118997295764
    },
    {
      "rank": 8,
      "construct": "child_qualities_conformity_tradition|WVS_A",
      "score": 0.7948626858651908
    },
    {
      "rank": 9,
      "construct": "freedom_security_tradeoff_perception|WVS_H",
      "score": 0.7947023122144848
    },
    {
      "rank": 10,
      "construct": "confidence_in_international_organizations|WVS_E",
      "score": 0.7943035643988285
    },
    {
      "rank": 11,
      "construct": "postmaterialist_values|WVS_E",
      "score": 0.7941088449452111
    },
    {
      "rank": 12,
      "construct": "subjective_wellbeing|WVS_A",
      "score": 0.7939226883553602
    },
    {
      "rank": 13,
      "construct": "basic_needs_deprivation|WVS_H",
      "score": 0.7938855061664691
    },
    {
      "rank": 14,
      "construct": "outgroup_trust|WVS_G",
      "score": 0.7922989175499726
    },
    {
      "rank": 15,
      "construct": "importance_of_life_domains|WVS_A",
      "score": 0.7920838012538922
    },
    {
      "rank": 16,
      "construct": "child_qualities_autonomy_self_expression|WVS_A",
      "score": 0.7915567612291134
    },
    {
      "rank": 17,
      "construct": "societal_change_attitudes|WVS_E",
      "score": 0.790727125326988
    },
    {
      "rank": 18,
      "construct": "precautionary_security_behaviors|WVS_H",
      "score": 0.7902369410838029
    },
    {
      "rank": 19,
      "construct": "work_ethic|WVS_C",
      "score": 0.7897410012520846
    },
    {
      "rank": 20,
      "construct": "familial_duty_obligations|WVS_D",
      "score": 0.7895052487983618
    },
    {
      "rank": 21,
      "construct": "perceived_positive_effects_of_immigration|WVS_G",
      "score": 0.7894801817776359
    },
    {
      "rank": 22,
      "construct": "authoritarian_governance_tolerance|WVS_E",
      "score": 0.7888344515779869
    },
    {
      "rank": 23,
      "construct": "gender_role_traditionalism|WVS_D",
      "score": 0.7886896742006353
    },
    {
      "rank": 24,
      "construct": "democratic_values_importance|WVS_E",
      "score": 0.7886716654769989
    },
    {
      "rank": 25,
      "construct": "science_technology_optimism|WVS_E",
      "score": 0.7885945527468761
    },
    {
      "rank": 26,
      "construct": "civic_dishonesty_tolerance|WVS_F",
      "score": 0.7881879576865941
    },
    {
      "rank": 27,
      "construct": "political_information_sources|WVS_E",
      "score": 0.7878565412035278
    },
    {
      "rank": 28,
      "construct": "female_income_threat_to_marriage|WVS_D",
      "score": 0.7877827396569949
    },
    {
      "rank": 29,
      "construct": "international_organization_knowledge|WVS_E",
      "score": 0.7869689996166872
    },
    {
      "rank": 30,
      "construct": "neighborhood_disorder_and_crime|WVS_H",
      "score": 0.7867284045148775
    },
    {
      "rank": 31,
      "construct": "existential_threat_worry|WVS_H",
      "score": 0.786208877399664
    },
    {
      "rank": 32,
      "construct": "perceived_corruption|WVS_E",
      "score": 0.7859742327072543
    },
    {
      "rank": 33,
      "construct": "acceptance_of_state_surveillance|WVS_H",
      "score": 0.7859719488720732
    },
    {
      "rank": 34,
      "construct": "religious_belief|WVS_F",
      "score": 0.7858077204655962
    },
    {
      "rank": 35,
      "construct": "science_skepticism|WVS_I",
      "score": 0.7843538472869336
    },
    {
      "rank": 36,
      "construct": "voluntary_association_active_membership|WVS_A",
      "score": 0.7843436693855536
    },
    {
      "rank": 37,
      "construct": "perceived_negative_effects_of_immigration|WVS_G",
      "score": 0.7832380581529996
    },
    {
      "rank": 38,
      "construct": "job_scarcity_gender_discrimination|WVS_C",
      "score": 0.7827809731568648
    },
    {
      "rank": 39,
      "construct": "voluntary_association_belonging|WVS_A",
      "score": 0.7819447935041812
    },
    {
      "rank": 40,
      "construct": "crime_victimization|WVS_H",
      "score": 0.7819016747413483
    },
    {
      "rank": 41,
      "construct": "voting_participation|WVS_E",
      "score": 0.7799546557032047
    },
    {
      "rank": 42,
      "construct": "autocracy_support|WVS_E",
      "score": 0.7797921094444039
    },
    {
      "rank": 43,
      "construct": "social_intolerance_outgroups|WVS_A",
      "score": 0.7788459204062287
    },
    {
      "rank": 44,
      "construct": "religion_versus_secularism_orientation|WVS_F",
      "score": 0.7784022218493228
    },
    {
      "rank": 45,
      "construct": "religious_practice_and_self_identification|WVS_F",
      "score": 0.7780820475837961
    },
    {
      "rank": 46,
      "construct": "life_autonomy_morality_permissiveness|WVS_F",
      "score": 0.7773469563809076
    },
    {
      "rank": 47,
      "construct": "violence_tolerance|WVS_F",
      "score": 0.7766555904472257
    },
    {
      "rank": 48,
      "construct": "sexual_and_reproductive_morality_permissiveness|WVS_F",
      "score": 0.7765865090458082
    },
    {
      "rank": 49,
      "construct": "job_scarcity_nativist_preference|WVS_C",
      "score": 0.7758747348530812
    },
    {
      "rank": 50,
      "construct": "religious_exclusivism|WVS_F",
      "score": 0.7753997590394521
    },
    {
      "rank": 51,
      "construct": "socioeconomic_insecurity_worry|WVS_H",
      "score": 0.7748310521727764
    },
    {
      "rank": 52,
      "construct": "online_political_participation|WVS_E",
      "score": 0.7735635690238043
    },
    {
      "rank": 53,
      "construct": "immigrant_origin_status|WVS_G",
      "score": 0.7601780451208611
    },
    {
      "rank": 54,
      "construct": "institutional_threat_perception|WVS_H",
      "score": 3.325386879748926e-08
    },
    {
      "rank": 55,
      "construct": "offline_political_participation|WVS_E",
      "score": 3.3253868769733685e-08
    }
  ],
  "sink_ranking": [
    {
      "rank": 1,
      "construct": "immigrant_origin_status|WVS_G",
      "score": 2.3351677632343057
    },
    {
      "rank": 2,
      "construct": "online_political_participation|WVS_E",
      "score": 1.4859541343826508
    },
    {
      "rank": 3,
      "construct": "socioeconomic_insecurity_worry|WVS_H",
      "score": 1.4797797513153612
    },
    {
      "rank": 4,
      "construct": "job_scarcity_nativist_preference|WVS_C",
      "score": 1.460158212303784
    },
    {
      "rank": 5,
      "construct": "religious_exclusivism|WVS_F",
      "score": 1.4337944153820743
    },
    {
      "rank": 6,
      "construct": "violence_tolerance|WVS_F",
      "score": 1.3850166248245477
    },
    {
      "rank": 7,
      "construct": "sexual_and_reproductive_morality_permissiveness|WVS_F",
      "score": 1.3801897295598702
    },
    {
      "rank": 8,
      "construct": "life_autonomy_morality_permissiveness|WVS_F",
      "score": 1.354298500215865
    },
    {
      "rank": 9,
      "construct": "religious_practice_and_self_identification|WVS_F",
      "score": 1.3019681475213631
    },
    {
      "rank": 10,
      "construct": "religion_versus_secularism_orientation|WVS_F",
      "score": 1.2946596635274594
    },
    {
      "rank": 11,
      "construct": "social_intolerance_outgroups|WVS_A",
      "score": 1.2621174034409157
    },
    {
      "rank": 12,
      "construct": "autocracy_support|WVS_E",
      "score": 1.1238475868971438
    },
    {
      "rank": 13,
      "construct": "voting_participation|WVS_E",
      "score": 1.1019570076896403
    },
    {
      "rank": 14,
      "construct": "crime_victimization|WVS_H",
      "score": 1.0661801520732095
    },
    {
      "rank": 15,
      "construct": "voluntary_association_belonging|WVS_A",
      "score": 1.0493436643345384
    },
    {
      "rank": 16,
      "construct": "job_scarcity_gender_discrimination|WVS_C",
      "score": 1.0084585297020046
    },
    {
      "rank": 17,
      "construct": "perceived_negative_effects_of_immigration|WVS_G",
      "score": 0.9853966773721488
    },
    {
      "rank": 18,
      "construct": "science_skepticism|WVS_I",
      "score": 0.9305030689880527
    },
    {
      "rank": 19,
      "construct": "voluntary_association_active_membership|WVS_A",
      "score": 0.8941392224576623
    },
    {
      "rank": 20,
      "construct": "existential_threat_worry|WVS_H",
      "score": 0.824925107810039
    },
    {
      "rank": 21,
      "construct": "religious_belief|WVS_F",
      "score": 0.817633594124346
    },
    {
      "rank": 22,
      "construct": "acceptance_of_state_surveillance|WVS_H",
      "score": 0.8105284027864543
    },
    {
      "rank": 23,
      "construct": "perceived_corruption|WVS_E",
      "score": 0.7971109986593704
    },
    {
      "rank": 24,
      "construct": "neighborhood_disorder_and_crime|WVS_H",
      "score": 0.7742346117298513
    },
    {
      "rank": 25,
      "construct": "female_income_threat_to_marriage|WVS_D",
      "score": 0.7404052309345093
    },
    {
      "rank": 26,
      "construct": "international_organization_knowledge|WVS_E",
      "score": 0.706213716422917
    },
    {
      "rank": 27,
      "construct": "civic_dishonesty_tolerance|WVS_F",
      "score": 0.7008995364562073
    },
    {
      "rank": 28,
      "construct": "gender_role_traditionalism|WVS_D",
      "score": 0.6733811850584052
    },
    {
      "rank": 29,
      "construct": "political_information_sources|WVS_E",
      "score": 0.6731038925877908
    },
    {
      "rank": 30,
      "construct": "science_technology_optimism|WVS_E",
      "score": 0.658237911771612
    },
    {
      "rank": 31,
      "construct": "democratic_values_importance|WVS_E",
      "score": 0.6467925478124646
    },
    {
      "rank": 32,
      "construct": "authoritarian_governance_tolerance|WVS_E",
      "score": 0.6314468338095569
    },
    {
      "rank": 33,
      "construct": "work_ethic|WVS_C",
      "score": 0.6198975104604146
    },
    {
      "rank": 34,
      "construct": "perceived_positive_effects_of_immigration|WVS_G",
      "score": 0.6118663178113696
    },
    {
      "rank": 35,
      "construct": "familial_duty_obligations|WVS_D",
      "score": 0.6079089425972547
    },
    {
      "rank": 36,
      "construct": "precautionary_security_behaviors|WVS_H",
      "score": 0.5782820989670191
    },
    {
      "rank": 37,
      "construct": "societal_change_attitudes|WVS_E",
      "score": 0.5242850098693022
    },
    {
      "rank": 38,
      "construct": "child_qualities_autonomy_self_expression|WVS_A",
      "score": 0.4906914358255345
    },
    {
      "rank": 39,
      "construct": "outgroup_trust|WVS_G",
      "score": 0.45333442226322435
    },
    {
      "rank": 40,
      "construct": "importance_of_life_domains|WVS_A",
      "score": 0.4469771686899413
    },
    {
      "rank": 41,
      "construct": "basic_needs_deprivation|WVS_H",
      "score": 0.3575236376244275
    },
    {
      "rank": 42,
      "construct": "subjective_wellbeing|WVS_A",
      "score": 0.35251913893528186
    },
    {
      "rank": 43,
      "construct": "postmaterialist_values|WVS_E",
      "score": 0.3379442923296574
    },
    {
      "rank": 44,
      "construct": "freedom_security_tradeoff_perception|WVS_H",
      "score": 0.31580818537430866
    },
    {
      "rank": 45,
      "construct": "confidence_in_international_organizations|WVS_E",
      "score": 0.31424251138935094
    },
    {
      "rank": 46,
      "construct": "child_qualities_conformity_tradition|WVS_A",
      "score": 0.30341538537907115
    },
    {
      "rank": 47,
      "construct": "child_qualities_prosocial_diligence|WVS_A",
      "score": 0.2896334089365216
    },
    {
      "rank": 48,
      "construct": "electoral_integrity|WVS_E",
      "score": 0.27885948143451733
    },
    {
      "rank": 49,
      "construct": "confidence_in_domestic_institutions|WVS_E",
      "score": 0.24063048448458346
    },
    {
      "rank": 50,
      "construct": "economic_ideology|WVS_E",
      "score": 0.21016363705318078
    },
    {
      "rank": 51,
      "construct": "multilevel_place_attachment|WVS_G",
      "score": 0.20444623174989762
    },
    {
      "rank": 52,
      "construct": "democratic_system_evaluation|WVS_E",
      "score": 0.20408186350018076
    },
    {
      "rank": 53,
      "construct": "confidence_in_civil_society_organizations|WVS_E",
      "score": 0.15302402530011563
    },
    {
      "rank": 54,
      "construct": "institutional_threat_perception|WVS_H",
      "score": 0.0
    },
    {
      "rank": 55,
      "construct": "offline_political_participation|WVS_E",
      "score": 0.0
    }
  ],
  "top_asymmetric_pairs": [
    {
      "source": "confidence_in_civil_society_organizations|WVS_E",
      "target": "immigrant_origin_status|WVS_G",
      "asymmetry": 0.04814860682180936
    },
    {
      "source": "electoral_integrity|WVS_E",
      "target": "immigrant_origin_status|WVS_G",
      "asymmetry": 0.047975074947656834
    },
    {
      "source": "freedom_security_tradeoff_perception|WVS_H",
      "target": "immigrant_origin_status|WVS_G",
      "asymmetry": 0.044431184189481755
    },
    {
      "source": "basic_needs_deprivation|WVS_H",
      "target": "immigrant_origin_status|WVS_G",
      "asymmetry": 0.04339252206103644
    },
    {
      "source": "economic_ideology|WVS_E",
      "target": "immigrant_origin_status|WVS_G",
      "asymmetry": 0.04112845388594619
    },
    {
      "source": "postmaterialist_values|WVS_E",
      "target": "immigrant_origin_status|WVS_G",
      "asymmetry": 0.038825690222441256
    },
    {
      "source": "child_qualities_autonomy_self_expression|WVS_A",
      "target": "immigrant_origin_status|WVS_G",
      "asymmetry": 0.038520928209587774
    },
    {
      "source": "civic_dishonesty_tolerance|WVS_F",
      "target": "immigrant_origin_status|WVS_G",
      "asymmetry": 0.0385100074327839
    },
    {
      "source": "child_qualities_conformity_tradition|WVS_A",
      "target": "immigrant_origin_status|WVS_G",
      "asymmetry": 0.037476222568303234
    },
    {
      "source": "confidence_in_domestic_institutions|WVS_E",
      "target": "immigrant_origin_status|WVS_G",
      "asymmetry": 0.036751103947616964
    },
    {
      "source": "subjective_wellbeing|WVS_A",
      "target": "immigrant_origin_status|WVS_G",
      "asymmetry": 0.036492662990130695
    },
    {
      "source": "importance_of_life_domains|WVS_A",
      "target": "immigrant_origin_status|WVS_G",
      "asymmetry": 0.03591821401357827
    },
    {
      "source": "authoritarian_governance_tolerance|WVS_E",
      "target": "immigrant_origin_status|WVS_G",
      "asymmetry": 0.035643122288787084
    },
    {
      "source": "multilevel_place_attachment|WVS_G",
      "target": "immigrant_origin_status|WVS_G",
      "asymmetry": 0.0356054553391166
    },
    {
      "source": "science_technology_optimism|WVS_E",
      "target": "immigrant_origin_status|WVS_G",
      "asymmetry": 0.03469393999054294
    },
    {
      "source": "religious_belief|WVS_F",
      "target": "immigrant_origin_status|WVS_G",
      "asymmetry": 0.03445644745741002
    },
    {
      "source": "child_qualities_prosocial_diligence|WVS_A",
      "target": "immigrant_origin_status|WVS_G",
      "asymmetry": 0.03444811863269751
    },
    {
      "source": "democratic_system_evaluation|WVS_E",
      "target": "immigrant_origin_status|WVS_G",
      "asymmetry": 0.03390325688925195
    },
    {
      "source": "societal_change_attitudes|WVS_E",
      "target": "immigrant_origin_status|WVS_G",
      "asymmetry": 0.032878346802181505
    },
    {
      "source": "existential_threat_worry|WVS_H",
      "target": "immigrant_origin_status|WVS_G",
      "asymmetry": 0.032391637830666134
    }
  ],
  "scenario": {
    "seed": "confidence_in_civil_society_organizations|WVS_E",
    "magnitude": 1.0,
    "shifts": [
      {
        "construct": "immigrant_origin_status|WVS_G",
        "shift": 0.05153212435802127
      },
      {
        "construct": "violence_tolerance|WVS_F",
        "shift": 0.035331237798927266
      },
      {
        "construct": "life_autonomy_morality_permissiveness|WVS_F",
        "shift": 0.032459952196294405
      },
      {
        "construct": "sexual_and_reproductive_morality_permissiveness|WVS_F",
        "shift": 0.03220233382932711
      },
      {
        "construct": "socioeconomic_insecurity_worry|WVS_H",
        "shift": 0.02883627140183044
      },
      {
        "construct": "religious_exclusivism|WVS_F",
        "shift": 0.028337936093750356
      },
      {
        "construct": "religion_versus_secularism_orientation|WVS_F",
        "shift": 0.02529920146732368
      },
      {
        "construct": "online_political_participation|WVS_E",
        "shift": 0.024580940330429166
      },
      {
        "construct": "job_scarcity_nativist_preference|WVS_C",
        "shift": 0.024276094409364377
      },
      {
        "construct": "religious_practice_and_self_identification|WVS_F",
        "shift": 0.024110913407646154
      },
      {
        "construct": "science_skepticism|WVS_I",
        "shift": 0.02261929825340018
      },
      {
        "construct": "voluntary_association_belonging|WVS_A",
        "shift": 0.021610366604797704
      },
      {
        "construct": "religious_belief|WVS_F",
        "shift": 0.021220100416128436
      },
      {
        "construct": "social_intolerance_outgroups|WVS_A",
        "shift": 0.019605936663924513
      },
      {
        "construct": "autocracy_support|WVS_E",
        "shift": 0.0195657329740042
      },
      {
        "construct": "voting_participation|WVS_E",
        "shift": 0.01815983479460977
      },
      {
        "construct": "job_scarcity_gender_discrimination|WVS_C",
        "shift": 0.01768021649869792
      },
      {
        "construct": "perceived_negative_effects_of_immigration|WVS_G",
        "shift": 0.017420711227936512
      },
      {
        "construct": "crime_victimization|WVS_H",
        "shift": 0.016473777646712293
      },
      {
        "construct": "civic_dishonesty_tolerance|WVS_F",
        "shift": 0.016041083803553575
      }
    ]
  },
  "mediator_correlation": {
    "spearman_rho": -0.37226501205572665,
    "p_value": 0.005130245853521692,
    "n_matched": 55,
    "interpretation": "weak agreement \u2014 PPR and mediator capture different aspects"
  },
  "alpha_sensitivity": {
    "per_alpha": {
      "0.10": [
        "confidence_in_civil_society_organizations|WVS_E",
        "multilevel_place_attachment|WVS_G",
        "democratic_system_evaluation|WVS_E",
        "economic_ideology|WVS_E",
        "confidence_in_domestic_institutions|WVS_E",
        "child_qualities_prosocial_diligence|WVS_A",
        "electoral_integrity|WVS_E",
        "child_qualities_conformity_tradition|WVS_A",
        "freedom_security_tradeoff_perception|WVS_H",
        "confidence_in_international_organizations|WVS_E",
        "postmaterialist_values|WVS_E",
        "subjective_wellbeing|WVS_A",
        "basic_needs_deprivation|WVS_H",
        "outgroup_trust|WVS_G",
        "importance_of_life_domains|WVS_A",
        "child_qualities_autonomy_self_expression|WVS_A",
        "societal_change_attitudes|WVS_E",
        "precautionary_security_behaviors|WVS_H",
        "work_ethic|WVS_C",
        "familial_duty_obligations|WVS_D",
        "perceived_positive_effects_of_immigration|WVS_G",
        "authoritarian_governance_tolerance|WVS_E",
        "gender_role_traditionalism|WVS_D",
        "democratic_values_importance|WVS_E",
        "science_technology_optimism|WVS_E",
        "political_information_sources|WVS_E",
        "civic_dishonesty_tolerance|WVS_F",
        "female_income_threat_to_marriage|WVS_D",
        "international_organization_knowledge|WVS_E",
        "neighborhood_disorder_and_crime|WVS_H",
        "acceptance_of_state_surveillance|WVS_H",
        "religious_belief|WVS_F",
        "existential_threat_worry|WVS_H",
        "perceived_corruption|WVS_E",
        "voluntary_association_active_membership|WVS_A",
        "science_skepticism|WVS_I",
        "perceived_negative_effects_of_immigration|WVS_G",
        "job_scarcity_gender_discrimination|WVS_C",
        "voluntary_association_belonging|WVS_A",
        "crime_victimization|WVS_H",
        "voting_participation|WVS_E",
        "autocracy_support|WVS_E",
        "social_intolerance_outgroups|WVS_A",
        "religion_versus_secularism_orientation|WVS_F",
        "religious_practice_and_self_identification|WVS_F",
        "life_autonomy_morality_permissiveness|WVS_F",
        "violence_tolerance|WVS_F",
        "sexual_and_reproductive_morality_permissiveness|WVS_F",
        "religious_exclusivism|WVS_F",
        "job_scarcity_nativist_preference|WVS_C",
        "socioeconomic_insecurity_worry|WVS_H",
        "online_political_participation|WVS_E",
        "immigrant_origin_status|WVS_G",
        "institutional_threat_perception|WVS_H",
        "offline_political_participation|WVS_E"
      ],
      "0.15": [
        "confidence_in_civil_society_organizations|WVS_E",
        "multilevel_place_attachment|WVS_G",
        "economic_ideology|WVS_E",
        "democratic_system_evaluation|WVS_E",
        "confidence_in_domestic_institutions|WVS_E",
        "child_qualities_prosocial_diligence|WVS_A",
        "electoral_integrity|WVS_E",
        "child_qualities_conformity_tradition|WVS_A",
        "freedom_security_tradeoff_perception|WVS_H",
        "confidence_in_international_organizations|WVS_E",
        "postmaterialist_values|WVS_E",
        "subjective_wellbeing|WVS_A",
        "basic_needs_deprivation|WVS_H",
        "outgroup_trust|WVS_G",
        "importance_of_life_domains|WVS_A",
        "child_qualities_autonomy_self_expression|WVS_A",
        "societal_change_attitudes|WVS_E",
        "precautionary_security_behaviors|WVS_H",
        "work_ethic|WVS_C",
        "familial_duty_obligations|WVS_D",
        "perceived_positive_effects_of_immigration|WVS_G",
        "authoritarian_governance_tolerance|WVS_E",
        "gender_role_traditionalism|WVS_D",
        "democratic_values_importance|WVS_E",
        "science_technology_optimism|WVS_E",
        "civic_dishonesty_tolerance|WVS_F",
        "political_information_sources|WVS_E",
        "female_income_threat_to_marriage|WVS_D",
        "international_organization_knowledge|WVS_E",
        "neighborhood_disorder_and_crime|WVS_H",
        "existential_threat_worry|WVS_H",
        "acceptance_of_state_surveillance|WVS_H",
        "perceived_corruption|WVS_E",
        "religious_belief|WVS_F",
        "voluntary_association_active_membership|WVS_A",
        "science_skepticism|WVS_I",
        "perceived_negative_effects_of_immigration|WVS_G",
        "job_scarcity_gender_discrimination|WVS_C",
        "voluntary_association_belonging|WVS_A",
        "crime_victimization|WVS_H",
        "voting_participation|WVS_E",
        "autocracy_support|WVS_E",
        "social_intolerance_outgroups|WVS_A",
        "religion_versus_secularism_orientation|WVS_F",
        "religious_practice_and_self_identification|WVS_F",
        "life_autonomy_morality_permissiveness|WVS_F",
        "violence_tolerance|WVS_F",
        "sexual_and_reproductive_morality_permissiveness|WVS_F",
        "job_scarcity_nativist_preference|WVS_C",
        "religious_exclusivism|WVS_F",
        "socioeconomic_insecurity_worry|WVS_H",
        "online_political_participation|WVS_E",
        "immigrant_origin_status|WVS_G",
        "institutional_threat_perception|WVS_H",
        "offline_political_participation|WVS_E"
      ],
      "0.20": [
        "confidence_in_civil_society_organizations|WVS_E",
        "multilevel_place_attachment|WVS_G",
        "economic_ideology|WVS_E",
        "democratic_system_evaluation|WVS_E",
        "confidence_in_domestic_institutions|WVS_E",
        "child_qualities_prosocial_diligence|WVS_A",
        "electoral_integrity|WVS_E",
        "child_qualities_conformity_tradition|WVS_A",
        "freedom_security_tradeoff_perception|WVS_H",
        "confidence_in_international_organizations|WVS_E",
        "postmaterialist_values|WVS_E",
        "subjective_wellbeing|WVS_A",
        "basic_needs_deprivation|WVS_H",
        "outgroup_trust|WVS_G",
        "importance_of_life_domains|WVS_A",
        "child_qualities_autonomy_self_expression|WVS_A",
        "societal_change_attitudes|WVS_E",
        "precautionary_security_behaviors|WVS_H",
        "work_ethic|WVS_C",
        "familial_duty_obligations|WVS_D",
        "perceived_positive_effects_of_immigration|WVS_G",
        "authoritarian_governance_tolerance|WVS_E",
        "gender_role_traditionalism|WVS_D",
        "democratic_values_importance|WVS_E",
        "science_technology_optimism|WVS_E",
        "civic_dishonesty_tolerance|WVS_F",
        "political_information_sources|WVS_E",
        "female_income_threat_to_marriage|WVS_D",
        "international_organization_knowledge|WVS_E",
        "neighborhood_disorder_and_crime|WVS_H",
        "existential_threat_worry|WVS_H",
        "perceived_corruption|WVS_E",
        "acceptance_of_state_surveillance|WVS_H",
        "religious_belief|WVS_F",
        "science_skepticism|WVS_I",
        "voluntary_association_active_membership|WVS_A",
        "perceived_negative_effects_of_immigration|WVS_G",
        "job_scarcity_gender_discrimination|WVS_C",
        "voluntary_association_belonging|WVS_A",
        "crime_victimization|WVS_H",
        "voting_participation|WVS_E",
        "autocracy_support|WVS_E",
        "social_intolerance_outgroups|WVS_A",
        "religion_versus_secularism_orientation|WVS_F",
        "religious_practice_and_self_identification|WVS_F",
        "life_autonomy_morality_permissiveness|WVS_F",
        "violence_tolerance|WVS_F",
        "sexual_and_reproductive_morality_permissiveness|WVS_F",
        "job_scarcity_nativist_preference|WVS_C",
        "religious_exclusivism|WVS_F",
        "socioeconomic_insecurity_worry|WVS_H",
        "online_political_participation|WVS_E",
        "immigrant_origin_status|WVS_G",
        "institutional_threat_perception|WVS_H",
        "offline_political_participation|WVS_E"
      ],
      "0.30": [
        "confidence_in_civil_society_organizations|WVS_E",
        "multilevel_place_attachment|WVS_G",
        "economic_ideology|WVS_E",
        "confidence_in_domestic_institutions|WVS_E",
        "democratic_system_evaluation|WVS_E",
        "child_qualities_prosocial_diligence|WVS_A",
        "child_qualities_conformity_tradition|WVS_A",
        "freedom_security_tradeoff_perception|WVS_H",
        "electoral_integrity|WVS_E",
        "confidence_in_international_organizations|WVS_E",
        "postmaterialist_values|WVS_E",
        "basic_needs_deprivation|WVS_H",
        "subjective_wellbeing|WVS_A",
        "outgroup_trust|WVS_G",
        "importance_of_life_domains|WVS_A",
        "child_qualities_autonomy_self_expression|WVS_A",
        "societal_change_attitudes|WVS_E",
        "precautionary_security_behaviors|WVS_H",
        "work_ethic|WVS_C",
        "familial_duty_obligations|WVS_D",
        "perceived_positive_effects_of_immigration|WVS_G",
        "authoritarian_governance_tolerance|WVS_E",
        "gender_role_traditionalism|WVS_D",
        "democratic_values_importance|WVS_E",
        "science_technology_optimism|WVS_E",
        "civic_dishonesty_tolerance|WVS_F",
        "female_income_threat_to_marriage|WVS_D",
        "political_information_sources|WVS_E",
        "neighborhood_disorder_and_crime|WVS_H",
        "international_organization_knowledge|WVS_E",
        "existential_threat_worry|WVS_H",
        "perceived_corruption|WVS_E",
        "acceptance_of_state_surveillance|WVS_H",
        "religious_belief|WVS_F",
        "science_skepticism|WVS_I",
        "voluntary_association_active_membership|WVS_A",
        "perceived_negative_effects_of_immigration|WVS_G",
        "job_scarcity_gender_discrimination|WVS_C",
        "crime_victimization|WVS_H",
        "voluntary_association_belonging|WVS_A",
        "autocracy_support|WVS_E",
        "voting_participation|WVS_E",
        "social_intolerance_outgroups|WVS_A",
        "religion_versus_secularism_orientation|WVS_F",
        "religious_practice_and_self_identification|WVS_F",
        "life_autonomy_morality_permissiveness|WVS_F",
        "violence_tolerance|WVS_F",
        "sexual_and_reproductive_morality_permissiveness|WVS_F",
        "job_scarcity_nativist_preference|WVS_C",
        "religious_exclusivism|WVS_F",
        "socioeconomic_insecurity_worry|WVS_H",
        "online_political_participation|WVS_E",
        "immigrant_origin_status|WVS_G",
        "institutional_threat_perception|WVS_H",
        "offline_political_participation|WVS_E"
      ],
      "0.50": [
        "confidence_in_civil_society_organizations|WVS_E",
        "multilevel_place_attachment|WVS_G",
        "economic_ideology|WVS_E",
        "confidence_in_domestic_institutions|WVS_E",
        "child_qualities_prosocial_diligence|WVS_A",
        "democratic_system_evaluation|WVS_E",
        "child_qualities_conformity_tradition|WVS_A",
        "freedom_security_tradeoff_perception|WVS_H",
        "electoral_integrity|WVS_E",
        "postmaterialist_values|WVS_E",
        "confidence_in_international_organizations|WVS_E",
        "basic_needs_deprivation|WVS_H",
        "subjective_wellbeing|WVS_A",
        "outgroup_trust|WVS_G",
        "importance_of_life_domains|WVS_A",
        "child_qualities_autonomy_self_expression|WVS_A",
        "precautionary_security_behaviors|WVS_H",
        "societal_change_attitudes|WVS_E",
        "familial_duty_obligations|WVS_D",
        "work_ethic|WVS_C",
        "perceived_positive_effects_of_immigration|WVS_G",
        "authoritarian_governance_tolerance|WVS_E",
        "gender_role_traditionalism|WVS_D",
        "science_technology_optimism|WVS_E",
        "democratic_values_importance|WVS_E",
        "civic_dishonesty_tolerance|WVS_F",
        "female_income_threat_to_marriage|WVS_D",
        "political_information_sources|WVS_E",
        "existential_threat_worry|WVS_H",
        "neighborhood_disorder_and_crime|WVS_H",
        "international_organization_knowledge|WVS_E",
        "perceived_corruption|WVS_E",
        "acceptance_of_state_surveillance|WVS_H",
        "religious_belief|WVS_F",
        "science_skepticism|WVS_I",
        "voluntary_association_active_membership|WVS_A",
        "perceived_negative_effects_of_immigration|WVS_G",
        "job_scarcity_gender_discrimination|WVS_C",
        "crime_victimization|WVS_H",
        "voluntary_association_belonging|WVS_A",
        "social_intolerance_outgroups|WVS_A",
        "autocracy_support|WVS_E",
        "voting_participation|WVS_E",
        "religion_versus_secularism_orientation|WVS_F",
        "religious_practice_and_self_identification|WVS_F",
        "life_autonomy_morality_permissiveness|WVS_F",
        "job_scarcity_nativist_preference|WVS_C",
        "violence_tolerance|WVS_F",
        "sexual_and_reproductive_morality_permissiveness|WVS_F",
        "socioeconomic_insecurity_worry|WVS_H",
        "religious_exclusivism|WVS_F",
        "online_political_participation|WVS_E",
        "immigrant_origin_status|WVS_G",
        "offline_political_participation|WVS_E",
        "institutional_threat_perception|WVS_H"
      ]
    },
    "stable_hubs": [
      "child_qualities_conformity_tradition|WVS_A",
      "child_qualities_prosocial_diligence|WVS_A",
      "confidence_in_civil_society_organizations|WVS_E",
      "confidence_in_domestic_institutions|WVS_E",
      "democratic_system_evaluation|WVS_E",
      "economic_ideology|WVS_E",
      "electoral_integrity|WVS_E",
      "freedom_security_tradeoff_perception|WVS_H",
      "multilevel_place_attachment|WVS_G"
    ],
    "sensitive_constructs": []
  }
}